linktools_setup/__init__.py
linktools_setup/build_meta.py
linktools_setup/setup.py
linktools_setup-0.0.1.post2.dist-info/licenses/LICENSE
linktools_setup-0.0.1.post2.dist-info/METADATA
linktools_setup-0.0.1.post2.dist-info/WHEEL
linktools_setup-0.0.1.post2.dist-info/entry_points.txt
linktools_setup-0.0.1.post2.dist-info/top_level.txt
linktools_setup-0.0.1.post2.dist-info/RECORD
